dirstory/__init__.py
dirstory/constants.py
dirstory/stack.py
dirstory/utils.py
dirstory/cli/__init__.py
dirstory/cli/cli.py
dirstory/cli/installation.py
dirstory/cli/list.py
dirstory/cli/navigate.py
dirstory/cli/stack.py
dirstory/scripts/__init__.py
dirstory/scripts/_dirstorypatch
dirstory/scripts/b
dirstory/scripts/f
dirstory-0.1.1.dist-info/LICENSE
dirstory-0.1.1.dist-info/METADATA
dirstory-0.1.1.dist-info/WHEEL
dirstory-0.1.1.dist-info/entry_points.txt
dirstory-0.1.1.dist-info/top_level.txt
dirstory-0.1.1.dist-info/RECORD
