Metadata-Version: 2.1
Name: dirstory
Version: 0.1.1
Summary: Navigate through the directories via command line as in file manager!
Home-page: https://github.com/nikromen/dirstory
Author: Jiří Kyjovský
Author-email: j1.kyjovsky@gmail.com
License: MIT
Requires-Python: >=3.7
License-File: LICENSE
Requires-Dist: click
Provides-Extra: testing
Requires-Dist: pytest ; extra == 'testing'
Requires-Dist: flexmock ; extra == 'testing'
